{"width":512,"imagePath":"ForestScorpion_tex.png","height":256,"name":"ForestScorpion","SubTexture":[{"frameHeight":19,"y":233,"frameX":-1,"width":290,"frameY":-1,"height":17,"name":"Ellipse 6","frameWidth":292,"x":1},{"width":72,"y":122,"height":79,"name":"legmir","x":287},{"frameHeight":19,"y":196,"frameX":-1,"width":29,"frameY":-1,"height":17,"name":"Layer 167","frameWidth":31,"x":183},{"width":102,"y":122,"height":72,"name":"Group 10","x":183},{"width":184,"y":1,"height":119,"name":"Layer 164","x":1},{"width":180,"y":122,"height":109,"name":"Layer 165","x":1},{"width":72,"y":122,"height":79,"name":"Layer 166","x":361}]}